youtubeaio/__init__.py
youtubeaio/const.py
youtubeaio/helper.py
youtubeaio/models.py
youtubeaio/oauth.py
youtubeaio/py.typed
youtubeaio/types.py
youtubeaio/youtube.py
youtubeaio-2.1.0.dist-info/METADATA
youtubeaio-2.1.0.dist-info/WHEEL
youtubeaio-2.1.0.dist-info/licenses/LICENSE.md
youtubeaio-2.1.0.dist-info/RECORD
